cognition_api/__init__.py
cognition_api/api.yaml
cognition_api/config.py
cognition_api/main.py
cognition_api/models.py
cognition_api/service.py
cognition_api/core/__init__.py
cognition_api/core/interface.py
cognition_api/middleware/__init__.py
cognition_api/middleware/logging.py
cognition_api/middleware/rate_limit.py
cognition_api/routes/__init__.py
cognition_api/routes/health.py
cognition_api/routes/openai.py
cognition_api/utils/__init__.py
cognition_api/utils/error_handler.py
cognition_api/utils/metrics.py
cognition_api/utils/task_manager.py
cognition_api-0.2.1.dist-info/METADATA
cognition_api-0.2.1.dist-info/WHEEL
cognition_api-0.2.1.dist-info/RECORD
