Metadata-Version: 2.4
Name: cognition-api
Version: 0.2.1
Summary: API layer for Cognition Core AI agents
Author-email: Nestor Colt <nestor.colt@gmail.com>
Requires-Python: <3.13,>=3.10
Requires-Dist: fastapi<1.0.0,>=0.109.0
Requires-Dist: httpx>=0.27.0
Requires-Dist: pydantic<3.0.0,>=2.0.0
Requires-Dist: uvicorn<1.0.0,>=0.27.0
Provides-Extra: dev
Requires-Dist: black>=24.0.0; extra == 'dev'
Requires-Dist: isort>=5.13.0; extra == 'dev'
Requires-Dist: pytest-asyncio>=0.23.0; extra == 'dev'
Requires-Dist: pytest>=7.0.0; extra == 'dev'
